cst816.py
circuitpython_cst816-0.1.0.dist-info/LICENSE
circuitpython_cst816-0.1.0.dist-info/METADATA
circuitpython_cst816-0.1.0.dist-info/WHEEL
circuitpython_cst816-0.1.0.dist-info/top_level.txt
circuitpython_cst816-0.1.0.dist-info/RECORD
