Metadata-Version: 2.1
Name: circuitpython-cst816
Version: 0.1.0
Summary: CircuitPython driver for the CST816 capacitive touch screen IC
Author: NeoStormer
License: MIT
Project-URL: Homepage, https://github.com/NeoStormer/CircuitPython_CST816
Keywords: adafruit,blinka,circuitpython,micropython,cst816,CST816,,CST816S,,CST816T,,touch,,display,,driver
Classifier: Intended Audience :: Developers
Classifier: Topic :: Software Development :: Libraries
Classifier: Topic :: Software Development :: Embedded Systems
Classifier: Topic :: System :: Hardware
Classifier: License :: OSI Approved :: MIT License
Classifier: Programming Language :: Python :: 3
License-File: LICENSE
Requires-Dist: Adafruit-Blinka
Requires-Dist: adafruit-circuitpython-busdevice
Provides-Extra: optional
